SqlAddImage/__init__.py
SqlAddImage-1.0.4.dist-info/LICENSE
SqlAddImage-1.0.4.dist-info/METADATA
SqlAddImage-1.0.4.dist-info/WHEEL
SqlAddImage-1.0.4.dist-info/top_level.txt
SqlAddImage-1.0.4.dist-info/RECORD
