Metadata-Version: 2.1
Name: SqlAddImage
Version: 1.0.4
Summary: SqlAddImage is a Python Package which helps user to insertand retrieve image in mysql database for particularfield by creating image column. 
Home-page: https://github.com/DeveloperHarshit09/SqlAddImage
Author: Easy Algorithm
Author-email: easyalgorithmsuccess@gmail.com
License: MIT
Requires-Python: >=3.7
License-File: LICENSE
Requires-Dist: mysql-connector-python
Requires-Dist: colorama
Requires-Dist: pillow
Requires-Dist: Python-IO
